colorman/__init__.py
colorman/box.py
colornal/__init__.py
colornal/box.py
tests/__init__.py
tests/colormantest.py
colornal-1.0.0.dist-info/METADATA
colornal-1.0.0.dist-info/WHEEL
colornal-1.0.0.dist-info/top_level.txt
colornal-1.0.0.dist-info/RECORD
