Metadata-Version: 2.1
Name: colornal
Version: 1.0.0
Summary: A package for creating colored boxes in the console
Home-page: https://github.com/rishicorp1/colorman.git
Author: Rishi
Author-email: technorishi1200@gmail.com
Classifier: Programming Language :: Python :: 3
Classifier: License :: OSI Approved :: MIT License
Classifier: Operating System :: OS Independent
Requires-Python: >=3.6
Requires-Dist: colorama
